[
  {
    "HeaderOffset": 429,
    "StartTextOffset": 435,
    "EndTextOffset": 439,
    "Text": "MSFE1"
  },
  {
    "HeaderOffset": 540,
    "StartTextOffset": 546,
    "EndTextOffset": 563,
    "Text": "synestheteHeadband"
  },
  {
    "HeaderOffset": 564,
    "StartTextOffset": 570,
    "EndTextOffset": 588,
    "Text": "Synesthetic Refocus"
  },
  {
    "HeaderOffset": 624,
    "StartTextOffset": 630,
    "EndTextOffset": 778,
    "Text": "Each face of this brilliant gem displays a differently-dimensioned, fractal reflection when looked into. Staring at it for too long hurts your eyes."
  },
  {
    "HeaderOffset": 779,
    "StartTextOffset": 785,
    "EndTextOffset": 808,
    "Text": "Armor.SynestheticRefocus"
  },
  {
    "HeaderOffset": 1143,
    "StartTextOffset": 1149,
    "EndTextOffset": 1161,
    "Text": "Psychokinesis"
  },
  {
    "HeaderOffset": 1325,
    "StartTextOffset": 1331,
    "EndTextOffset": 1340,
    "Text": "Perception"
  },
  {
    "HeaderOffset": 1461,
    "StartTextOffset": 1467,
    "EndTextOffset": 1476,
    "Text": "Perception"
  }
]