[
  {
    "HeaderOffset": 272,
    "StartTextOffset": 278,
    "EndTextOffset": 304,
    "Text": "component.shieldEmitterBase"
  },
  {
    "HeaderOffset": 305,
    "StartTextOffset": 311,
    "EndTextOffset": 329,
    "Text": "Shield Emitter Base"
  },
  {
    "HeaderOffset": 365,
    "StartTextOffset": 371,
    "EndTextOffset": 412,
    "Text": "The base part of an energy shield emitter."
  },
  {
    "HeaderOffset": 413,
    "StartTextOffset": 419,
    "EndTextOffset": 432,
    "Text": "Components.230"
  },
  {
    "HeaderOffset": 683,
    "StartTextOffset": 689,
    "EndTextOffset": 699,
    "Text": "Electronics"
  }
]